README.md
setup.cfg
setup.py
high_entropy_string/__init__.py
high_entropy_string.egg-info/PKG-INFO
high_entropy_string.egg-info/SOURCES.txt
high_entropy_string.egg-info/dependency_links.txt
high_entropy_string.egg-info/requires.txt
high_entropy_string.egg-info/top_level.txt